diffs/__init__.py
diffs/diffs.py
tests/__init__.py
tests/helpers.py
tests/test_clean_diffs.py
tests/test_diff_info.py
Dev101-0.0.2.dist-info/LICENSE
Dev101-0.0.2.dist-info/METADATA
Dev101-0.0.2.dist-info/WHEEL
Dev101-0.0.2.dist-info/top_level.txt
Dev101-0.0.2.dist-info/RECORD
