Metadata-Version: 2.1
Name: Dev101
Version: 0.0.2
Summary: A tool for automating the creation of software engineering tutorials
Home-page: https://github.com/andrewrobles/Dev101
Author: Andrew Robles
Author-email: andrewroblesdev@gmail.com
License: UNKNOWN
Platform: UNKNOWN
Classifier: Programming Language :: Python :: 3
Classifier: License :: OSI Approved :: MIT License
Classifier: Operating System :: OS Independent
Requires-Python: >=3.6
Requires-Dist: GitPython (==3.1.11)
